README
setup.cfg
setup.py
swim.py
mywiki/__init__.py
mywiki/manage.py
mywiki/settings.py
mywiki/urls.py
mywiki/views.py
pyswim.egg-info/PKG-INFO
pyswim.egg-info/SOURCES.txt
pyswim.egg-info/dependency_links.txt
pyswim.egg-info/not-zip-safe
pyswim.egg-info/requires.txt
pyswim.egg-info/top_level.txt
resources/headbg.jpg
resources/main.css
resources/outgoing_link.gif
