Metadata-Version: 1.0
Name: pyswim
Version: 0.2
Summary: Static WIkipedia Mirror
Home-page: http://pyswim.googlecode.com
Author: Xie Yanbo
Author-email: xieyanbo@gmail.com
License: BSD
Download-URL: http://pyswim.googlecode.com
Platform: UNKNOWN
Classifier: Development Status :: 2 - Pre-Alpha
Classifier: Environment :: Console
Classifier: Environment :: Web Environment
Classifier: Framework :: Django
Classifier: License :: OSI Approved :: GNU General Public License (GPL)
Classifier: Operating System :: POSIX :: Linux
Classifier: Programming Language :: Python
Classifier: Topic :: Education
